sknrf
